mcp4py/__init__.py
mcp4py/client/__init__.py
mcp4py/client/exceptions.py
mcp4py/client/mcpc.py
mcp4py/server/__init__.py
mcp4py/server/config.py
mcp4py/server/mcps.py
mcp4py/server/api/__init__.py
mcp4py/server/api/demo.py
mcp4py/server/api/prompts.py
mcp4py/server/api/resources.py
mcp4py/server/api/tools.py
mcp4py/server/models/__init__.py
mcp4py/server/models/items.py
mcp4py/utils/__init__.py
mcp4py/utils/logger.py
mcp4py-0.8.0.dist-info/LICENSE
mcp4py-0.8.0.dist-info/METADATA
mcp4py-0.8.0.dist-info/WHEEL
mcp4py-0.8.0.dist-info/top_level.txt
mcp4py-0.8.0.dist-info/RECORD
