Metadata-Version: 2.2
Name: mcp4py
Version: 0.8.0
Summary: My awesome Python project
Author-email: XuehangCang <xuehangcang@outlook.com>
License: MIT License
Classifier: Programming Language :: Python :: 3
Classifier: License :: OSI Approved :: MIT License
Classifier: Operating System :: OS Independent
Requires-Python: >=3.9
License-File: LICENSE
Requires-Dist: fastapi>=0.115.11
Requires-Dist: uvicorn>=0.34.0
Requires-Dist: requests>=2.32.3
Provides-Extra: dev
Requires-Dist: pytest; extra == "dev"
Requires-Dist: flake8; extra == "dev"
